gwfp/__init__.py
gwfp/gwfp.py
gwfp/settings.py
gwfp-0.0.2.dist-info/LICENSE.txt
gwfp-0.0.2.dist-info/METADATA
gwfp-0.0.2.dist-info/WHEEL
gwfp-0.0.2.dist-info/entry_points.txt
gwfp-0.0.2.dist-info/top_level.txt
gwfp-0.0.2.dist-info/RECORD
