Metadata-Version: 2.1
Name: gwfp
Version: 0.0.2
Summary: Get Connected Wi-fi data easily.
Home-page: https://github.com/RaghavGohil/GWFP
Author: RaghavGohil
Author-email: raghavgohil2004@gmail.com
License: MIT LICENSE
Keywords: Forgotten wifi password get
Platform: UNKNOWN
Classifier: Development Status :: 1 - Planning
Classifier: License :: OSI Approved :: MIT License
Classifier: Operating System :: Microsoft
Requires-Python: >=3.0
Requires-Dist: regex (>=2022.3.15)
Requires-Dist: readme-renderer (>=21.0)
